hw/rtl/updownCounter.sv
// 8-bit up/down binary counter with async reset and parallel load
`timescale 1ns / 1ps

module updownCounter (
    input logic Clock,
    Reset,
    Enable,
    LoadEn,
    Up1Dn0,
    input logic [7:0] LoadData,
    output logic [7:0] Q
);
  always_ff @(posedge Clock or posedge Reset) begin
    if (Reset) begin
      Q <= 8'b0;
    end else if (LoadEn) begin
      Q <= LoadData;
    end else if (Enable) begin
      if (Up1Dn0) begin
        Q <= Q + 8'd1;
      end else begin
        Q <= Q - 8'd1;
      end
    end
  end
endmodule

hw/tb/updownCounter_tb.sv
`timescale 1ns / 1ps

module updownCounter_tb;
  logic Clock;
  logic Reset;
  logic Enable;
  logic Load;
  logic Up1Dn0;
  logic [7:0] Data;
  logic [7:0] Q;

  updownCounter dut (
      .Clock(Clock),
      .Reset(Reset),
      .Enable(Enable),
      .LoadEn(Load),
      .Up1Dn0(Up1Dn0),
      .LoadData(Data),
      .Q(Q)
  );

  // 100 MHz clock: period = 10 ns
  initial Clock = 1'b0;
  always #5 Clock = ~Clock;

  initial begin
    $display("Starting updownCounter_tb...");
    $dumpfile("updownCounter_tb.vcd");
    $dumpvars(0, updownCounter_tb);

    // Initial values
    Reset  = 1'b0;
    Enable = 1'b0;
    Load   = 1'b0;
    Up1Dn0 = 1'b1;
    Data   = 8'h00;

    // Test 1: asynchronous reset
    #2;
    Reset = 1'b1;
    #1;
    if (Q !== 8'h00) $error("Reset failed: expected 0x00, got %0h", Q);
    #7;
    Reset = 1'b0;

    // Test 2: load priority over enable
    @(posedge Clock);
    Data   = 8'h3C;
    Load   = 1'b1;
    Enable = 1'b1;
    Up1Dn0 = 1'b1;

    @(posedge Clock);
    if (Q !== 8'h3C) $error("Load failed: expected 0x3C, got %0h", Q);
    Load = 1'b0;

    // Test 3: count up
    @(posedge Clock);
    if (Q !== 8'h3D) $error("Count up failed: expected 0x3D, got %0h", Q);

    // Test 4: hold when enable is low
    Enable = 1'b0;
    @(posedge Clock);
    if (Q !== 8'h3D) $error("Hold failed: expected 0x3D, got %0h", Q);

    // Test 5: count down
    Enable = 1'b1;
    Up1Dn0 = 1'b0;
    @(posedge Clock);
    if (Q !== 8'h3C) $error("Count down failed: expected 0x3C, got %0h", Q);

    // Test 6: up wrap-around (FF -> 00)
    Load = 1'b1;
    Data = 8'hFF;
    @(posedge Clock);
    Load   = 1'b0;
    Up1Dn0 = 1'b1;
    @(posedge Clock);
    if (Q !== 8'h00) $error("Up wrap failed: expected 0x00, got %0h", Q);

    // Test 7: down wrap-around (00 -> FF)
    Up1Dn0 = 1'b0;
    @(posedge Clock);
    if (Q !== 8'hFF) $error("Down wrap failed: expected 0xFF, got %0h", Q);

    $display("Testbench completed.");
    #10;
    $finish;
  end
endmodule

updownCounter_tb.vcd
$version Generated by VerilatedVcd $end
$timescale 1ps $end
 $scope module updownCounter_tb $end
  $var wire 1 ' Clock $end
  $var wire 1 " Reset $end
  $var wire 1 # Enable $end
  $var wire 1 $ Load $end
  $var wire 1 % Up1Dn0 $end
  $var wire 8 & Data [7:0] $end
  $var wire 8 ( Q [7:0] $end
  $scope module dut $end
   $var wire 1 ' Clock $end
   $var wire 1 " Reset $end
   $var wire 1 # Enable $end
   $var wire 1 $ LoadEn $end
   $var wire 1 % Up1Dn0 $end
   $var wire 8 & LoadData [7:0] $end
   $var wire 8 ( Q [7:0] $end
  $upscope $end
 $upscope $end
$enddefinitions $end


#0
0"
0#
0$
1%
b00000000 &
0'
b00000000 (
#2000
1"
#5000
1'
#10000
0"
0'
#15000
1#
1$
b00111100 &
1'
b00111100 (
#20000
0'
#25000
0$
1'
b00111101 (
#30000
0'
#35000
0#
1'
#40000
0'
#45000
1#
0%
1'
b00111100 (
#50000
0'
#55000
1$
b11111111 &
1'
b11111111 (
#60000
0'
#65000
0$
1%
1'
b00000000 (
#70000
0'
#75000
0%
1'
b11111111 (
#80000
0'
#85000
1'
b11111110 (
#90000
0'
#95000
1'
b11111101 (
